davai/__init__.py
davai/cli/__init__.py
davai/cli/experiment.py
davai/cli/host.py
davai/cli/shelf.py
davai/cli/util.py
davai/cli/conf/__init__.py
davai/cli/conf/atos_bologna.ini
davai/cli/conf/base.ini
davai/cli/conf/belenos.ini
davai/cli/conf/taranis.ini
davai/cli/scripts/__init__.py
davai/cli/scripts/build.py
davai/cli/scripts/ciboulai_init.py
davai/cli/scripts/config.py
davai/cli/scripts/cwd_is_xp.py
davai/cli/scripts/get_xp_path.py
davai/cli/scripts/new_xp.py
davai/cli/scripts/new_xp_from_bundle.py
davai/cli/scripts/run_tests.py
davai/cli/scripts/run_xp.py
davai/cli/scripts/shelf.py
davai/cli/scripts/tests_version.py
davai/cli/scripts/xp_status.py
davai/vtx/__init__.py
davai/vtx/util.py
davai/vtx/algo/__init__.py
davai/vtx/algo/build.py
davai/vtx/algo/mixins.py
davai/vtx/algo/reporting.py
davai/vtx/data/__init__.py
davai/vtx/data/info.py
davai/vtx/hooks/__init__.py
davai/vtx/hooks/namelists.py
davai/vtx/hooks/summaries.py
davai/vtx/tasks/__init__.py
davai/vtx/tasks/mixins.py
tasks/__init__.py
tasks/ciboulai_xpsetup.py
tasks/template.py
tasks/assim/BA1_3D_arome.py
tasks/assim/BSM_3D_arome.py
tasks/assim/BS_3D_arome__obstype.py
tasks/assim/BS_3D_arpege__obstype.py
tasks/assim/BS_4D_arpege__obstype.py
tasks/assim/BsC_arpege.py
tasks/assim/CNT0BSM_3D_arpege.py
tasks/assim/CNT0BSM_4D_arpege.py
tasks/assim/OOPSBA1_4D_arpege.py
tasks/assim/OOPSBSM_3D_arpege.py
tasks/assim/OOPSBSM_4D_arpege.py
tasks/assim/__init__.py
tasks/assim/minims/Analyse4dvar.py
tasks/assim/minims/AnalyseOOPS_LAM3D.py
tasks/assim/minims/__init__.py
tasks/assim/minims/minimCNT0.py
tasks/assim/minims/minimCNT0_LAM3D.py
tasks/assim/minims/minimOOPS.py
tasks/assim/minims/minimOOPS_LAM3D.py
tasks/assim/raw2odb/__init__.py
tasks/assim/raw2odb/batodb.py
tasks/assim/screenings/__init__.py
tasks/assim/screenings/screeningCNT0.py
tasks/assim/screenings/screeningOOPS.py
tasks/assim/screenings/screening_LAM3D.py
tasks/assim/surface/canari.py
tasks/build/__init__.py
tasks/build/wait4build.py
davai-2.0.2.dist-info/LICENSE
davai-2.0.2.dist-info/METADATA
davai-2.0.2.dist-info/WHEEL
davai-2.0.2.dist-info/entry_points.txt
davai-2.0.2.dist-info/top_level.txt
davai-2.0.2.dist-info/RECORD
