Metadata-Version: 2.2
Name: davai
Version: 2.0.2
Summary: Davai environment: commandlines for running DAVAI-tests experiments.
Author-email: Alexandre Mary <alexandre.mary@meteo.fr>
License: CECILL-C
Project-URL: source, https://github.com/ACCORD-NWP/DAVAI.git
Project-URL: tracker, https://github.com/ACCORD-NWP/DAVAI/issues
Requires-Python: >=3.10
License-File: LICENSE
Requires-Dist: footprints
Requires-Dist: pyyaml
Requires-Dist: ial_build==1.3.3
Requires-Dist: bronx
Requires-Dist: epygram==2.0.3
Requires-Dist: ial_build==1.3.3
Requires-Dist: ial_expertise[all]==1.2.4
Requires-Dist: requests[socks]
Requires-Dist: jinja2
